[
  {
    "request_date": "2018-12-12T01:06:54.456Z",
    "solicitor_client": "Katrine Bahringer",
    "venue": "molestiae",
    "start_date": "2020-06-16T13:42:19.104Z",
    "end_date": "2020-04-07T00:05:49.045Z",
    "type": "tempora",
    "template_ref": "omnis",
    "patient_name": "Audie Konopelski",
    "address": "3502 Luna Station Apt. 901, West Reannabury",
    "tel": "684-636-3417",
    "notes": "Rerum autem tempora.",
    "action": ""
  },
  {
    "request_date": "2019-06-18T10:00:09.637Z",
    "solicitor_client": "Freeman Spencer Sr.",
    "venue": "et",
    "start_date": "2020-03-25T19:39:33.023Z",
    "end_date": "2020-01-05T08:51:13.177Z",
    "type": "doloremque",
    "template_ref": "animi",
    "patient_name": "Mariah Medhurst",
    "address": "971 Scarlett Heights Suite 962, Auertown",
    "tel": "572-194-5263",
    "notes": "Est sint officia consequatur et corporis.",
    "action": ""
  },
  {
    "request_date": "2019-11-05T18:27:37.767Z",
    "solicitor_client": "Marianne Smith",
    "venue": "officia",
    "start_date": "2020-10-06T01:26:22.531Z",
    "end_date": "2020-03-24T20:01:57.496Z",
    "type": "perferendis",
    "template_ref": "ut",
    "patient_name": "Tremaine Altenwerth",
    "address": "2949 Paucek Centers Suite 116, North Kellishire",
    "tel": "213-942-7965",
    "notes": "Neque quia qui sit ex officia velit.",
    "action": ""
  },
  {
    "request_date": "2019-04-01T00:10:51.498Z",
    "solicitor_client": "Adella Walker",
    "venue": "et",
    "start_date": "2020-01-20T14:15:05.648Z",
    "end_date": "2020-11-08T11:36:46.553Z",
    "type": "provident",
    "template_ref": "cum",
    "patient_name": "Jameson Padberg",
    "address": "2036 Dixie Islands Suite 318, Tromphaven",
    "tel": "892-881-9598",
    "notes": "Consectetur et minus.",
    "action": ""
  },
  {
    "request_date": "2019-08-03T03:48:13.180Z",
    "solicitor_client": "Marlen Beier",
    "venue": "eos",
    "start_date": "2019-11-16T14:04:27.925Z",
    "end_date": "2020-02-11T11:47:03.154Z",
    "type": "magni",
    "template_ref": "distinctio",
    "patient_name": "Brown Considine",
    "address": "931 Deondre Burgs Apt. 529, Lake Caseytown",
    "tel": "996-636-0648",
    "notes": "Omnis laudantium ex unde quam asperiores cumque.",
    "action": "",
    "status": "overdue report"
  },
  {
    "request_date": "2019-01-31T11:10:42.678Z",
    "solicitor_client": "Garland Daugherty",
    "venue": "inventore",
    "start_date": "2020-03-11T08:22:06.548Z",
    "end_date": "2020-04-07T17:21:18.326Z",
    "type": "at",
    "template_ref": "esse",
    "patient_name": "Willow Frami",
    "address": "7214 Schuster Dam Suite 464, Lake Bobbieland",
    "tel": "858-665-3706",
    "notes": "Maiores sed reiciendis ullam.",
    "action": "",
    "status": "overdue report"
  },
  {
    "request_date": "2019-02-28T08:31:42.987Z",
    "solicitor_client": "Bethany Adams",
    "venue": "ut",
    "start_date": "2020-11-09T19:34:29.603Z",
    "end_date": "2020-08-05T04:44:12.367Z",
    "type": "nemo",
    "template_ref": "voluptas",
    "patient_name": "Zetta Bergstrom PhD",
    "address": "04644 Harris Forges Apt. 412, East Estel",
    "tel": "950-565-2267",
    "notes": "Sequi pariatur accusamus.",
    "action": "",
    "status": "overdue report"
  },
  {
    "request_date": "2019-05-21T07:18:49.083Z",
    "solicitor_client": "Sammie Smitham",
    "venue": "sint",
    "start_date": "2020-10-09T05:21:20.316Z",
    "end_date": "2020-02-14T14:28:28.810Z",
    "type": "eius",
    "template_ref": "quia",
    "patient_name": "Triston McCullough",
    "address": "49913 Kassulke Loop Apt. 879, East Keeganton",
    "tel": "960-784-4617",
    "notes": "Voluptatem voluptates nobis est ipsam.",
    "action": ""
  },
  {
    "request_date": "2018-11-17T22:20:04.718Z",
    "solicitor_client": "Lourdes Reichert",
    "venue": "magni",
    "start_date": "2020-07-05T20:23:39.358Z",
    "end_date": "2020-08-11T04:09:56.399Z",
    "type": "pariatur",
    "template_ref": "numquam",
    "patient_name": "Elmer Marvin",
    "address": "615 Williamson Roads Suite 650, Rohanbury",
    "tel": "159-804-4135",
    "notes": "Cumque ipsam adipisci est et minus vero.",
    "action": "",
    "status": "missed exam"
  }
]
